{
	"miniprogramRoot": "dist/",
	"projectname": "taro-gm",
	"description": "play",
	"appid": "wx877f937ab2a1949e",
	"setting": {
		"urlCheck": false,
		"es6": false,
		"enhance": false,
		"postcss": false,
		"preloadBackgroundData": false,
		"minified": false,
		"newFeature": true,
		"coverView": true,
		"nodeModules": false,
		"autoAudits": false,
		"showShadowRootInWxmlPanel": true,
		"scopeDataCheck": false,
		"uglifyFileName": false,
		"checkInvalidKey": true,
		"checkSiteMap": true,
		"uploadWithSourceMap": true,
		"compileHotReLoad": false,
		"babelSetting": {
			"ignore": [],
			"disablePlugins": [],
			"outputPath": ""
		},
		"useIsolateContext": true,
		"useCompilerModule": true,
		"userConfirmedUseCompilerModuleSwitch": false
	},
	"compileType": "miniprogram",
	"simulatorType": "wechat",
	"simulatorPluginLibVersion": {},
	"condition": {}
}